{
  "name": "",  
  "content": "I absolutely **hate** scoping projects.  It\u0026#39;s such uninteresting / uninspiring work.  \n\nIt\u0026#39;s ironic because scoping generally translates to work/dollars, so it\u0026#39;s a critical part of my business.\n\nAlso, I can\u0026#39;t outsource this task. I don\u0026#39;t trust anyone to do it correctly and accurately\n\n",
  "permalink" : "https://brandon_swoop.ngrok.io/2018/12/04/63943/",
  "date":"2018-12-04T17:45:43Z","draft":false,"iscjklanguage":false,"lastmod":"2018-12-04T17:45:43Z","post_type":"note","publishdate":"2018-12-04T17:45:43Z","slug":"63943","type":"post"
}