{
  "name": "This Pretty Much Sums It Up",  
  "content": "\u003cimg class=\"alignnone\" title=\"This Pretty Much Sums It Up\" src=\"http://i.imgur.com/hf0oR.png\" alt=\"\" width=\"300\" height=\"300\" /\u003e\n\n[Source][1]\n\n\u003cdiv style=\"\"\u003e\n  \u003ca href=\"http://twitter.com/share\" class=\"twitter-share-button\" data-count=\"horizontal\" data-text=\"This Pretty Much Sums It Up\" data-url=\"http://brandontreb.com/this-pretty-much-sums-it-up\"  data-via=\"brandontreb\" data-related=\"brandontreb:\"\u003eTweet\u003c/a\u003e\n\u003c/div\u003e\n\n [1]: http://www.reddit.com/r/pics/comments/dh8g0/actually_this_pretty_much_sums_it_up_as_well/\n",
  "permalink" : "https://brandon_swoop.ngrok.io/2010/09/22/this-pretty-much-sums-it-up/",
  "date":"2010-09-22T00:00:00Z","draft":false,"iscjklanguage":false,"lastmod":"2010-09-22T00:00:00Z","post_type":"article","publishdate":"2010-09-22T00:00:00Z","slug":"this-pretty-much-sums-it-up","tags":["Articles"],"title":"This Pretty Much Sums It Up","type":"post"
}