{
  "name": "",  
  "content": "Lazy ducks are lazy 🦆 \n\n\n![](/uploads/2020/03313a2e-fa30-479a-b469-b36329d03d99.jpeg)\n",
  "permalink" : "https://brandontreb.ngrok.io/2020/11/09/73211/",
  "date":"2020-11-09T20:20:11Z","draft":false,"iscjklanguage":false,"lastmod":"2020-11-09T20:20:11Z","photos":[{"alt":null,"path":"uploads/2020/03313a2e-fa30-479a-b469-b36329d03d99.jpeg","url":"https://brandon_swoop.ngrok.io/uploads/2020/03313a2e-fa30-479a-b469-b36329d03d99.jpeg"}],"post_type":"photo","publishdate":"2020-11-09T20:20:11Z","slug":"73211","tags":["Homestead","ducks"],"type":"post"
}