{
  "name": "",  
  "content": "I have never seen micro.blog so active. It must be because of **The Great Twitter Exodus**. I understand the hate for Musk, however I don\u0026#39;t understand how him buying the company makes it any _worse_.  \n\n**Prediction**: Everyone leaves today and re-activates their account in a month. \n\n",
  "permalink" : "https://brandon_swoop.ngrok.io/2022/04/26/70666/",
  "date":"2022-04-26T19:37:46Z","draft":false,"iscjklanguage":false,"lastmod":"2022-04-26T19:37:46Z","post_type":"note","publishdate":"2022-04-26T19:37:46Z","slug":"70666","type":"post"
}